LICENSE.txt
MANIFEST.in
README.rst
setup.py
pygments_pvs/__init__.py
pygments_pvs/lexer.py
pygments_pvs.egg-info/PKG-INFO
pygments_pvs.egg-info/SOURCES.txt
pygments_pvs.egg-info/dependency_links.txt
pygments_pvs.egg-info/entry_points.txt
pygments_pvs.egg-info/requires.txt
pygments_pvs.egg-info/top_level.txt
pygments_pvs.egg-info/zip-safe