Metadata-Version: 1.1
Name: pygments-pvs
Version: 0.1
Summary: Pygments lexer for PVS source files
Home-page: https://github.com/Elarnon/pygments-pvs
Author: Basile Clement
Author-email: basile@clement.pm
License: MIT
Download-URL: https://github.com/Elarnon/pygments-pvs/archive/0.1.tar.gz
Platform: UNKNOWN
Classifier: Development Status :: 3 - Alpha
Classifier: Environment :: Plugins
Classifier: License :: OSI Approved :: MIT License
Classifier: Programming Language :: Python
Classifier: Programming Language :: Python :: 2
Classifier: Programming Language :: Python :: 3
Classifier: Operating System :: OS Independent
Classifier: Intended Audience :: Developers
Classifier: Topic :: Software Development :: Libraries :: Python Modules
